setup.py
logsanitizer/__init__.py
logsanitizer/tests.py
logsanitizer.egg-info/PKG-INFO
logsanitizer.egg-info/SOURCES.txt
logsanitizer.egg-info/dependency_links.txt
logsanitizer.egg-info/entry_points.txt
logsanitizer.egg-info/not-zip-safe
logsanitizer.egg-info/requires.txt
logsanitizer.egg-info/top_level.txt