Metadata-Version: 1.0
Name: logsanitizer
Version: 0.1.2
Summary: Log processing and sanitizer tool written in Python.
Home-page: http://6wunderkinder.com
Author: Bence Faludi
Author-email: befaludi@microsoft.com
License: MIT
Platform: UNKNOWN
